salam/__init__.py
salam/salam.py
salam/salam_paras.inp
salam/inputScripts/PG003__bat_sdf_to_gscom.sh
salam/inputScripts/PG006__bat_g09log_to_propcom.sh
salam/inputScripts/__init__.py
salam/inputScripts/b3lyp-gs-opt-model-com
salam/inputScripts/b3lyp-nlo-model-com
salam/inputScripts/b3lyp-tadf-model-com
salam/inputScripts/bat-g16-opt-freq.sh
salam/inputScripts/bat-g16-prop.sh
salam/inputScripts/bat-g16.sh
salam/inputScripts/bat-remove-unfinished-com.sh
salam/inputScripts/bat_node130_133.sh
salam/inputScripts/camb3lyp-nlo-model-com
salam/inputScripts/camb3lyp-tadf-model-com
salam/inputScripts/cis-tadf-model-com
salam/inputScripts/copy_com_chk_logs_to_modification_finished.sh
salam/inputScripts/g16.pbs.sh
salam/inputScripts/g16_node130_133.pbs.sh
salam/inputScripts/gs-opt-model-com
salam/inputScripts/lcwpbe-tadf-model-com
salam/inputScripts/pm6d3-gs-opt-model-com
salam/inputScripts/pm7-gs-opt-model-com
salam/inputScripts/tadf-model-comput-com
salam/inputScripts/wb97xd-nlo-model-com
salam/inputScripts/wb97xd-tadf-model-com
salam/inputScripts/zindo-tadf-model-com
salam/module_MD/Crossover.py
salam/module_MD/D_Pi_A_Enumeration.py
salam/module_MD/Metrics.py
salam/module_MD/OrganoMetalics_Enumeration.py
salam/module_MD/__init__.py
salam/module_MD/SA_Score/UnitTestSAScore.py
salam/module_MD/SA_Score/__init__.py
salam/module_MD/SA_Score/sascorer.py
salam/project/__init__.py
salam/project/G0000/G0000.sdf
salam/project/G0000/__init__.py
salam/src/PG001__Generate_G0000.py
salam/src/PG002__MaxMinPicker.py
salam/src/PG003__bat_sdf_to_gscom.py
salam/src/PG004__bat_qsub_jobs_opt.py
salam/src/PG005__optimization_analysis_completeness.py
salam/src/PG006__bat_g09log_to_propcom.py
salam/src/PG007__bat_qsub_jobs_prop.py
salam/src/PG008__property_analysis_completeness.py
salam/src/PG009__property_analysis_summary.py
salam/src/PG010__featurizers_train_evaluate.py
salam/src/PG011__predict_opt_molecules.py
salam/src/PG012__Generate_Gnew.py
salam/src/PG012a__Generate_Gnew_Debranch.py
salam-0.0.2a5.dist-info/LICENSE.txt
salam-0.0.2a5.dist-info/METADATA
salam-0.0.2a5.dist-info/WHEEL
salam-0.0.2a5.dist-info/entry_points.txt
salam-0.0.2a5.dist-info/top_level.txt
salam-0.0.2a5.dist-info/RECORD
