Metadata-Version: 2.1
Name: salam
Version: 0.0.2a5
Summary: A Python tool for high-throughput virtual screening of organic molecules driven by structural crossover, mutation and machine learning.
Home-page: https://github.com/yidapa/salam
Author: Chunyun Jacob Tu
Author-email: yidapa@yeah.net
License: MIT
Project-URL: Bug Reports, https://github.com/yidapa/salam/issues
Project-URL: Source, https://github.com/yidapa/salam/
Keywords: machine learning,high-throughput virtual screening,chemoinformatics,molecular similarity,structural crossover,structural mutation
Platform: UNKNOWN
Classifier: Development Status :: 3 - Alpha
Classifier: Intended Audience :: Developers
Classifier: Topic :: Scientific/Engineering :: Chemistry
Classifier: License :: OSI Approved :: MIT License
Classifier: Programming Language :: Python :: 3
Classifier: Programming Language :: Python :: 3.7
Classifier: Programming Language :: Python :: 3.8
Classifier: Programming Language :: Python :: 3.9
Classifier: Programming Language :: Python :: 3.10
Classifier: Programming Language :: Python :: 3 :: Only
Requires-Python: >=3.7, <=3.10
License-File: LICENSE.txt
Requires-Dist: numpy (>=1.18.5)
Requires-Dist: scipy (>=1.6.0)
Requires-Dist: rdkit (>=2020.09.1.0)
Requires-Dist: pandas (>=1.1.5)
Requires-Dist: matplotlib (>=3.3.4)
Requires-Dist: scikit-learn (>=1.0.2)
Requires-Dist: joblib (>=1.0.0)
Requires-Dist: tqdm (>=4.59.0)
Requires-Dist: deepchem (>=2.5.0)
